Metadata-Version: 2.1
Name: python-keycloak-jea
Version: 0.26.1
Summary: python-keycloak is a Python package providing access to the Keycloak API.
Home-page: https://bitbucket.org/j-and-a/python-keycloak-jea.git
Author: Leandro de Souza
Author-email: marcospereira.mpj@gmail.com
License: The MIT License
Download-URL: https://bitbucket.org/j-and-a/python-keycloak-jea/get/release0.1.tar.gz
Keywords: keycloak openid jea
Platform: UNKNOWN
Classifier: Programming Language :: Python :: 3
Classifier: License :: OSI Approved :: MIT License
Classifier: Development Status :: 3 - Alpha
Classifier: Operating System :: MacOS
Classifier: Operating System :: Unix
Classifier: Operating System :: Microsoft :: Windows
Classifier: Topic :: Utilities
